quickgrpc/__init__.py
quickgrpc/utils.py
quickgrpc/helpers/__init__.py
quickgrpc/helpers/file.py
quickgrpc/helpers/misc.py
quickgrpc/helpers/vcs.py
quickgrpc-0.1.3.data/scripts/create_grpc_service
quickgrpc-0.1.3.data/scripts/publish_grpc_service
quickgrpc-0.1.3.data/scripts/servegrpc
quickgrpc-0.1.3.dist-info/LICENSE
quickgrpc-0.1.3.dist-info/METADATA
quickgrpc-0.1.3.dist-info/WHEEL
quickgrpc-0.1.3.dist-info/top_level.txt
quickgrpc-0.1.3.dist-info/RECORD
