Metadata-Version: 2.1
Name: quickgrpc
Version: 0.1.3
Summary: quickgrpc lib library
Home-page: https://github.com/ashupednekar
Author: Ashutosh Pednekar
Author-email: ashupednekar49@gmail.com
Project-URL: Source, https://github.com/ashupednekar/quickgrpc
Project-URL: Documentation, https://ashupednekar.github.io/quickgrpc
Project-URL: Bug Tracker, https://github.com/ashupednekar/quickgrpc/issues
Classifier: Programming Language :: Python
Classifier: Programming Language :: Python :: 3.9
Classifier: Programming Language :: Python :: 3.10
Classifier: Operating System :: OS Independent
License-File: LICENSE
Requires-Dist: typer ==0.12.3
Requires-Dist: openapi3-parser ==1.1.10
Requires-Dist: black ==23.3.0
Requires-Dist: isort ==5.12.0
Requires-Dist: tqdm ==4.66.1
Requires-Dist: pydantic ~=2.7.1
Requires-Dist: pydantic-settings ==2.2.1
Requires-Dist: grpcio-tools ==1.60.1
